{
  "cities": [
    {
      "cityName": "Peralejos",
      "country": "Spain",
      "emoji": "🇪🇸",
      "date": "2023-12-22T11:57:31.482Z",
      "notes": "",
      "position": {
        "lat": 40.478292268560175,
        "lng": -1.0025024414062502
      },
      "id": 2
    },
    {
      "cityName": "Santa Eulalia",
      "country": "Spain",
      "emoji": "🇪🇸",
      "date": "2023-12-22T11:57:39.997Z",
      "notes": "",
      "position": {
        "lat": 40.57954165275019,
        "lng": -1.2208557128906252
      },
      "id": 3
    },
    {
      "cityName": "Langa de Duero",
      "country": "Spain",
      "emoji": "🇪🇸",
      "date": "2023-12-22T11:58:03.095Z",
      "notes": "",
      "position": {
        "lat": 41.52400142852431,
        "lng": -3.4304809570312504
      },
      "id": 4
    }
  ]
}